{"parse_152774":{"time":1551731591,"expire":86400,"data":"\"{\\\"hotel\\\":[{\\\"address\\\":{\\\"country\\\":{\\\"id\\\":118593,\\\"name\\\":\\\"Slovenia\\\"},\\\"city\\\":{\\\"id\\\":152774,\\\"name\\\":\\\"Izola\\\"},\\\"street\\\":\\\"Dobrava 1 a\\\",\\\"postcode\\\":\\\"6310\\\"},\\\"hotelCategory\\\":{\\\"id\\\":4,\\\"category\\\":4,\\\"code\\\":\\\"FOUR\\\",\\\"name\\\":\\\"4*\\\"},\\\"services\\\":{},\\\"id\\\":322369,\\\"name\\\":\\\"Cliff\\\",\\\"status\\\":\\\"active\\\",\\\"isMixTypeAllowed\\\":true},{\\\"address\\\":{\\\"country\\\":{\\\"id\\\":118593,\\\"name\\\":\\\"Slovenia\\\"},\\\"city\\\":{\\\"id\\\":152774,\\\"name\\\":\\\"Izola\\\"},\\\"street\\\":\\\"DOBRAVA 1 A\\\",\\\"postcode\\\":\\\"6310\\\",\\\"latitude\\\":45.53048,\\\"longitude\\\":13.63389},\\\"hotelCategory\\\":{\\\"id\\\":3,\\\"category\\\":3,\\\"code\\\":\\\"THREE\\\",\\\"name\\\":\\\"3*\\\"},\\\"services\\\":{},\\\"id\\\":122879,\\\"name\\\":\\\"BELVEDERE\\\",\\\"status\\\":\\\"active\\\",\\\"isMixTypeAllowed\\\":true},{\\\"address\\\":{\\\"country\\\":{\\\"id\\\":118593,\\\"name\\\":\\\"Slovenia\\\"},\\\"city\\\":{\\\"id\\\":152774,\\\"name\\\":\\\"Izola\\\"},\\\"street\\\":\\\"Morova 6A\\\",\\\"postcode\\\":\\\"\\\",\\\"latitude\\\":45.53088,\\\"longitude\\\":13.64983},\\\"hotelCategory\\\":{\\\"id\\\":4,\\\"category\\\":4,\\\"code\\\":\\\"FOUR\\\",\\\"name\\\":\\\"4*\\\"},\\\"services\\\":{},\\\"id\\\":277261,\\\"name\\\":\\\"Haliaetum\\\\\\\/Mirta\\\",\\\"status\\\":\\\"active\\\",\\\"isMixTypeAllowed\\\":true},{\\\"address\\\":{\\\"country\\\":{\\\"id\\\":118593,\\\"name\\\":\\\"Slovenia\\\"},\\\"city\\\":{\\\"id\\\":152774,\\\"name\\\":\\\"Izola\\\"},\\\"street\\\":\\\"Cesta V Jagodje 1\\\",\\\"postcode\\\":\\\"SI-6310\\\",\\\"latitude\\\":45.52912,\\\"longitude\\\":13.64972},\\\"hotelCategory\\\":{\\\"id\\\":2,\\\"category\\\":2,\\\"code\\\":\\\"TWO\\\",\\\"name\\\":\\\"2*\\\"},\\\"services\\\":{},\\\"id\\\":210796,\\\"name\\\":\\\"Keltika\\\",\\\"status\\\":\\\"active\\\",\\\"isMixTypeAllowed\\\":true},{\\\"address\\\":{\\\"country\\\":{\\\"id\\\":118593,\\\"name\\\":\\\"Slovenia\\\"},\\\"city\\\":{\\\"id\\\":152774,\\\"name\\\":\\\"Izola\\\"},\\\"street\\\":\\\"Korte 74\\\",\\\"postcode\\\":\\\"6310\\\",\\\"latitude\\\":45.48919,\\\"longitude\\\":13.66256},\\\"hotelCategory\\\":{\\\"id\\\":1,\\\"category\\\":1,\\\"code\\\":\\\"ONE\\\",\\\"name\\\":\\\"1*\\\"},\\\"services\\\":{},\\\"id\\\":197873,\\\"name\\\":\\\"Hostel Stara sola Korte\\\",\\\"status\\\":\\\"inactive\\\",\\\"isMixTypeAllowed\\\":true},{\\\"address\\\":{\\\"country\\\":{\\\"id\\\":118593,\\\"name\\\":\\\"Slovenia\\\"},\\\"city\\\":{\\\"id\\\":152774,\\\"name\\\":\\\"Izola\\\"},\\\"street\\\":\\\"Morova 6A\\\",\\\"postcode\\\":\\\"\\\"},\\\"hotelCategory\\\":{\\\"id\\\":8,\\\"category\\\":8,\\\"code\\\":\\\"VLA\\\",\\\"name\\\":\\\"Villa\\\"},\\\"services\\\":{},\\\"id\\\":321448,\\\"name\\\":\\\"Vile 3* San Simon\\\",\\\"status\\\":\\\"active\\\",\\\"isMixTypeAllowed\\\":true},{\\\"address\\\":{\\\"country\\\":{\\\"id\\\":118593,\\\"name\\\":\\\"Slovenia\\\"},\\\"city\\\":{\\\"id\\\":152774,\\\"name\\\":\\\"Izola\\\"},\\\"street\\\":\\\"Veliki trg 11\\\",\\\"postcode\\\":\\\"6310\\\"},\\\"hotelCategory\\\":{\\\"id\\\":3,\\\"category\\\":3,\\\"code\\\":\\\"THREE\\\",\\\"name\\\":\\\"3*\\\"},\\\"services\\\":{\\\"long\\\":[12,51,10,18,19,8,9,11,52,49,5,21,27,41,74,26,24,28,55,29,50,54,40,39,31,32,34,35,46,45,44,43]},\\\"id\\\":122897,\\\"name\\\":\\\"Hotel Marina\\\",\\\"status\\\":\\\"active\\\",\\\"isMixTypeAllowed\\\":true}],\\\"version\\\":1551731588071}\""}}